sstk/__init__.py
sstk/__version__.py
sstk-0.1.dev0.dist-info/LICENSE
sstk-0.1.dev0.dist-info/METADATA
sstk-0.1.dev0.dist-info/WHEEL
sstk-0.1.dev0.dist-info/top_level.txt
sstk-0.1.dev0.dist-info/RECORD
